tesco/__init__.py
tesco/main.py
tesco-1.1.0.dist-info/WHEEL
tesco-1.1.0.dist-info/METADATA
tesco-1.1.0.dist-info/RECORD
