Metadata-Version: 2.1
Name: tesco
Version: 1.1.0
Summary: 
Home-page: https://github.com/pbexe/tesco
License: MIT
Author: Miles Budden
Author-email: miles@budden.net
Requires-Python: >=3.7,<4.0
Classifier: License :: OSI Approved :: MIT License
Classifier: Programming Language :: Python :: 3
Classifier: Programming Language :: Python :: 3.7
Classifier: Programming Language :: Python :: 3.8
Requires-Dist: requests (>=2.23.0,<3.0.0)
